sortwiz/__init__.py
sortwiz/__main__.py
sortwiz/base_sort.py
sortwiz/bubble_sort.py
sortwiz/quicksort.py
sortwiz/sorting.py
sortwiz-0.2.0.dist-info/LICENSE
sortwiz-0.2.0.dist-info/METADATA
sortwiz-0.2.0.dist-info/WHEEL
sortwiz-0.2.0.dist-info/entry_points.txt
sortwiz-0.2.0.dist-info/top_level.txt
sortwiz-0.2.0.dist-info/RECORD
