Metadata-Version: 2.1
Name: sortwiz
Version: 0.2.0
Summary: Apply sorting algorithms to python lists.
Author-email: Roberto Betini Junior <betini.roberto@gmail.com>
License: MIT License
Project-URL: Homepage, https://github.com/robertobetini/sortwiz
Keywords: sort,order,sorting,list
Classifier: License :: OSI Approved :: MIT License
Classifier: Programming Language :: Python
Classifier: Programming Language :: Python :: 3
Requires-Python: >=3.9
License-File: LICENSE
